<?xml version="1.0" encoding="iso-8859-1" ?>

<newsset>
  <news date="2004-08-02">
    <title>Open letter to IBM</title>
    <body>"
      Softwarepatenten zullen de basis vernietigen van IBM's toekomst":<br />

      "Iedereen zou tegen nu goed genoeg moeten begrijpen dat een wapenwedloop
      bijna nooit productief is. Het leidt tot een onhoudbare groei van ballast
      tot voorbij enige nuttige proporties tot slechts één deelnemer in die race
      overblijft. U mag denken dat IBM degene zou zijn die overleeft en u zou
      gelijk kunnen hebben.<br />

      Maar het resultaat van die deelneming in de wapenwedloop is dat IBM
      langzaam aan misvormd wordt. Het spendeert meer en meer energie aan een
      wapenwedloop die meer en meer in twijfel getrokken wordt."
    </body>
    <link>/projects/swpat/letter-20040802.html</link>
  </news>
</newsset>
