<?xml version="1.0" encoding="UTF-8"?>

<infoset>
  <info id="pin-plussy-green">
    <name>Fellowship speld</name>
    <description>
      <p>
        Een pin met het Fellowship-logo.
      </p>
    </description>
  </info>

  <info id="magnetpin-plussy-green">
    <name>Fellowship speld</name>
    <description>
      <p>
        Dezelfde speld, nu met magneet.
      </p>
    </description>
  </info>

  <info id="cufflinks-plussy-green">
    <name>Fellowship manchetknopen</name>
    <description>
      <p>
       Prijs per paar.
      </p>
    </description>
  </info>

  <info id="pin-gnu-silver">
    <name>Gnu speld</name>
    <description>
      <p>
        Een speld met Gnu en de tekst  "Free Software Foundation Europe".
      </p>
    </description>
  </info>

  <info id="magnetpin-gnu-silver">
    <name>Gnu speld</name>
    <description>
      <p>
        Dezelfde speld, nu met magneet.
      </p>
    </description>
  </info>

  <info id="cufflinks-gnu-silver">
    <name>Gnu manchetknopen</name>
    <description>
      <p>
        Prijs per paar.
      </p>
    </description>
  </info>
</infoset>
