<?xml version="1.0" encoding="UTF-8"?>

<!-- Do not translate this file! -->

<itemset>
  <item type="tshirt" id="tshirt-fsfs-yellow" price="10.00" oldprice="18.00" date="2012-10-06">
    <available size="S"/>
    <image
      small="2012/tshirt-fsfs-yellow-front-small.jpg"
      large="2012/tshirt-fsfs-yellow-front-large.jpg"/>
    <image
      small="2012/tshirt-fsfs-yellow-back-small.jpg"
      large="2012/tshirt-fsfs-yellow-back-large.jpg"/>
  </item>

  <!-- item type="tshirt" id="tshirt-ilovefs-black" price="10.00" oldprice="18.00" date="2012-10-06">
    <available size="S"/>
    <available size="M"/>
    <available size="XL"/>
    <image
      small="2012/tshirt-ilovefs-black-front-small.jpg"
      large="2012/tshirt-ilovefs-black-front-large.jpg"/>
    <image
      small="2012/tshirt-ilovefs-black-back-small.jpg"
      large="2012/tshirt-ilovefs-black-back-large.jpg"/>
  </item -->

  <item type="girlie" id="girlie-hacking-black" price="10.00" oldprice="18.00" date="2012-10-06">
    <available size="S"/>
    <available size="M"/>
    <available size="L"/>
    <available size="XL"/>
    <image
      small="2012/girlie-hacking-black-front-small.jpg"
      large="2012/girlie-hacking-black-front-large.jpg"/>
    <image
      small="2012/girlie-hacking-black-back-small.jpg"
      large="2012/girlie-hacking-black-back-large.jpg"/>
  </item>

  <item type="hooded" id="hoodie-plussy-black" price="35.00" date="2012-10-06">
    <available size="S"/>
    <image
      small="2012/hoodie-plussy-black-front-small.jpg"
      large="2012/hoodie-plussy-black-front-large.jpg"/>
    <image
      small="2012/hoodie-plussy-black-back-small.jpg"
      large="2012/hoodie-plussy-black-back-large.jpg"/>
  </item>

  <item type="other" id="pin-plussy-green" price="3.00" date="2012-10-06">
    <available size="#"/>
    <image
      small="2012/pin-plussy-green-small.jpg"
      large="2012/pin-plussy-green-large.jpg"/>
  </item>

  <item type="other" id="magnetpin-plussy-green" price="3.00" date="2012-10-06">
    <available size="#"/>
    <!-- same picture as the non-magnet pin -->
    <image
      small="2012/pin-plussy-green-small.jpg"
      large="2012/pin-plussy-green-large.jpg"/>
  </item>

  <item type="other" id="cufflinks-plussy-green" price="8.00" date="2012-10-06">
    <available size="#"/>
    <image
      small="2012/cufflinks-plussy-green-small.jpg"
      large="2012/cufflinks-plussy-green-large.jpg"/>
  </item>

  <item type="other" id="pin-gnu-silver" price="10.00" date="2012-10-06">
    <available size="#"/>
    <image
      small="2012/pin-gnu-silver-small.jpg"
      large="2012/pin-gnu-silver-large.jpg"/>
  </item>

  <item type="other" id="magnetpin-gnu-silver" price="10.00" date="2012-10-06">
    <available size="#"/>
    <!-- same picture as the non-magnet pin -->
    <image
      small="2012/pin-gnu-silver-small.jpg"
      large="2012/pin-gnu-silver-large.jpg"/>
  </item>
</itemset>
