<?xml version="1.0" encoding="utf-8"?>
<eventset>
  <version>1</version>
  <event start="2020-11-21" end="2020-11-21">
        <title>FOSSCOMM 2020: Denaro pubblico? Codice pubblico! durante il coronavirus - Che ruolo ha avuto il Software Libero durante la crisi? (online)</title>

    <body>
      <p>Il 21 novembre, alle 12:00 (CET), Alexander Sander, il responsabile delle politiche della FSFE, farà un intervento al FOSSCOMM 2020. In un tempo dove l'umanità ha bisogno di lavorare insieme per trovare una soluzione alla crisi, non possiamo permetterci di reinventare ogni volta la ruota. Problemi mondiali necessitano di soluzioni globali! Il Software Libero permette una cooperazione globale per lo sviluppo del codice. Nel suo discorso, Alexander Sander spiegherà che ruolo ha avuto il Software Libero durante la pandemia e come i governi hanno reagito. Non c'è bisogno di registrazione per partecipare, ma se si vuole rimanere informati è possibile registrarsi <a href="https://2020.fosscomm.gr/eggrafi-parakoloythisis/">qui</a>.</p>
    </body>

    <link>https://pretalx.2020.fosscomm.gr/fosscomm-2020/talk/V3GTG8/</link>
    <tags>
            <tag key="talk"/>
      <tag key="front-page"/>
    </tags>
  </event>
</eventset>
