<?xml version="1.0" encoding="UTF-8" ?>

<documentset>
  <version>1</version>

  <document type="political" date="2003-11-04">
    <title>Fighting intellectual poverty</title>
    <description>
      Article by <a href="/about/people/greve/">Georg Greve</a> for a publication of
      the <a href="http://www.boell.de">Heinrich Böll Foundation</a> on the
      <a href="/activities/wsis/">World Summit on the Information Society</a>
      (WSIS)
    </description>
    <link>/activities/wsis/issues.html</link>
  </document>
</documentset>
