<?xml version="1.0" encoding="UTF-8"?>
<quotes>
    <quote>
      <photo>/fellowship/graphics/people/hugoroy.png</photo>
      <text>
        Европейский фонд свободного программного обеспечения (ЕФСПО)
        сводит вместе постоянных и вовлеченных активистов со всей Европы,
        чтобы использовать возможности защитить наши права использовать,
        распространять, изучать и модифицировать программы, поскольку без
        свободных программ техника подчиняет нас вместо того, чтобы
        увеличивать нашу свободу.
      </text>
      <author>Гюго Руа (исследователь права)</author>
    </quote>
</quotes>
