<?xml version="1.0" encoding="utf-8"?>
<associateset>
  <version>1</version>

  <associate id="ceata">
    <name>(Fundația Ceata) مؤسسة التمويل</name>
    <description>
   
<p>مؤسسة (Fundația Ceata) هي مؤسسة رومانية للبرمجيات الحرة والثقافة الحرة، تتماشى مع فلسفة البرمجيات الحرة لمشروع GNU. تأسست في بوخارست، ولديها فرق محلية في مقاطعة كلوج وجمهورية مولدوفا. بدأت (Ceata) (كلمة رومانية تعني “العصابة”) كمجموعة غير رسمية في يونيو/حزيران ٢٠٠٨ وغدت مؤسسة في فبراير/شباط ٢٠١٣. منذ بدايتها، شاركت مؤسسة (Ceata) بصورة كبيرة في نشاط البرمجيات الحرة، وفي تنظيم فعاليات الحرية الرقمية، وفي تطوير كل من البرمجيات الحرة ومصنفات الثقافة الحرة.</p>
    </description>
    <link>https://ceata.org/</link>
  </associate>
</associateset>
