<?xml version="1.0" encoding="UTF-8" ?>
 
<eventset>
    <event start="2006-04-07" end="2006-04-07">
       <title>Softwarepatenter, ophavsret og GPLv3</title>
          <body>
	    Ciaran O'Riordan og Gareth Bowker vil holde en tale i London om
	    hvorfor og hvad FSFE gør for at forhindre lovmæssig overlast på
	    softwarefrihed - overlast så som den, der forårsages ved patentering
	    af software eller forvanskning af ophavsret.  O'Riordan vil også 
	    diskutere GPLv3 og dens over et år lange offentlige høringsproces.
	    Begge talere vil besvare spørgsmål.
          </body>
	  <page>http://ossg.bcs.org/organisation/website/news/patentscopyright070406</page>
    </event>  
</eventset> 
