<?xml version="1.0" encoding="utf-8"?>

<eventset>
  <version>1</version>

	<event start="2017-03-31" end="2017-04-01">

		<title>Takim i Kujdestarëve të Wiki-t në Esen, Gjermani</title>

		<body>
			<p>Wiki është një mjet i rëndësishëm për stafin dhe veprimtarët e FSFE-së në ndarjen e dijes me të tjerët, në dokumentimin e veprimtarive, dhe furnizimin e informacionit mbi grupet vendore. Është e rëndësishme që përdorimi i tij është pa shumë yçkla dhe joshës dhe që informacioni atje të jetë i strukturuar mirë, që të mund të gjendet dhe zgjerohet me lehtësi. Kjo lyp mirëmbajtje të vazhdueshme, të lëndës dhe mënyrës së punës. Ky takim do të japë bazat për këto veprimtari mirëmbajtjeje. Do të shërbejë edhe si fillim i Sprintit vjetor të Wiki-it.</p>
		</body>

		<link>https://wiki.fsfe.org/Teams/WikiCaretakers/Hackathon2017</link>


		<tags>
			<tag key="essen">Esen</tag>
			<tag key="de">Gjermani</tag>
			<tag key="front-page"/>
		</tags>


	</event>
</eventset>

