<?xml version="1.0" encoding="utf-8"?>

<eventset> 
  <event start="2016-08-20" end="2016-08-21"> 
 
    <title>FrOSCon 11 in St. Augustin, Deutschland</title> 
 
    <body> 
      <p>Die FrOSCon ist eine Freie-Software-Konferenz, die vom Fachbereich Informatik der Hochschule Bonn-Rhein-Sieg und anderen lokalen Initiativen organisiert wird. Besucher erwartet ein aufregendes Programm mit Vortr채gen und Workshops f체r jedes Alter. Die FSFE wird mit einem Stand vertreten sein sowie mit zwei Vortr채gen von <a href="https://programm.froscon.de/2016/events/1797.html">Polina Malaja</a> und <a href="https://programm.froscon.de/2016/events/1738.html">Max Mehl</a>. Wir freuen uns darauf, mit Ihnen 체ber Freie Software, Technik und Politik zu reden.</p> 
       
    </body> 
 
    <link>http://www.froscon.de/</link> 
 
    <tags>
      <tag content="FrOSCon">Froscon</tag>      
      <tag content="St. Augustin">St. Augustin</tag>
      <tag content="Deutschland">DE</tag>
      <tag content="Informationsstand">booth</tag>
      <tag>front-page</tag>
    </tags>

  </event> 
</eventset> 
