<?xml version="1.0" encoding="UTF-8"?>

<eventset>
  <version>1</version>

  <event start="2011-04-09" end="2011-04-09">
    <title>Free Software Workshop in Würzburg</title>
    <body>
      <p>At this year's "Landesjugendkongress", organised by the youth wing of 
      the German Green Party, Björn Schießle will hold a workshop about Free
      Software. The workshop will take place in Würzburg, Germany.
      </p>
    </body>
    <link>http://www.gj-bayern.de/kongress.html</link>
    <tags>
      <tag>front-page</tag>
      <tag>de</tag>
    </tags>
  </event>
</eventset>
