<?xml version="1.0" encoding="UTF-8"?>

<eventset>
  <version>1</version>

  <event start="2011-03-03" end="2011-03-03">
    <title>Izlaganje na CeBIT-u</title>
    <body>
      <p>FSFE-ov predsjednik Karsten Gerloff održat će izlaganje na
      <a href="http://www.cebit.de/home">CeBIT-u</a>, 
	  Hannover, Njemačka. Govorit će o "Slobodi, softveru i moći" 3. ožujka u
      15:30. Izlaganje će se održati u dvorani 2, paviljon F40.</p>
    </body>
    <tags>
      <tag>front-page</tag>

      <tag>talk</tag>
    </tags>
  </event>
</eventset>
