<?xml version="1.0" encoding="UTF-8"?>

<eventset>
  <version>1</version>

  <event start="2013-04-11" end="2013-04-11">
    <title>Berlin Fellowship meeting</title>
    <body>
	<p>Am 11.April ist es wieder mal an der Zeit für Berlins nächstes Fellowshipmeeting und es findet statt in der <a href="http://zope2.in-berlin.de:8100/wsb/elok/jc-e-lok">e-lok</a> (nähe Ostkreuz). Es gibt viele Themen, darunter der Verlauf des DFD, der Berliner Linuxtag und ein geplantes Koordinatorentreffen. </p>
	<p>Wie gewohnt ist das Fellowship meeting eine gute Gelegenheit andere Fellows zu treffen sowie andere Freunde Freier Software. Außerdem gibt es in der e-lok gutes Essen und Getränke zu angenehmen Preisen, gute Stimmung ist kostenlos. Offizieller Beginn ist 19.30.</p>
    </body>
    <tags>
      <tag>front-page</tag>
      <tag>de</tag>

      <tag>fellowship</tag>
    </tags>
  </event>
</eventset>
