<?xml version="1.0" encoding="UTF-8"?>

<newsset>

  <news date="2018-03-29">


    <title>Fellowship elections 2017 with eight candidates</title>

 
<body>
  

  
	<p newsteaser="yes">As <a href="https://fsfe.org/about/legal/constitution.en.html#id-fellowship-seats">written in FSFE's constitution</a>, two seats in the <a href="https://fsfe.org/about/team#general-assembly">General Assembly</a> are up for election among Fellows of the FSFE. The election period in 2017 runs from April 10 to April 24, 2017, with eight candidates eligible for election. You can find their personal motivation and presentation of the candidates on our dedicated <a href="https://wiki.fsfe.org/Migrated/FellowshipElection_2017">Fellowship Election 2017</a> page. In addition, there will be moderated hustings in FSFE's IRC channel in the evenings of March 30 and 31. Please find the detailed schedule and how you can participate at the bottom of our <a href="https://wiki.fsfe.org/Migrated/FellowshipElection_2017#Hustings">Fellowship Election 2017 page</a>. All orderly Fellows allowed to vote will receive an individual email that includes all information you need to know to vote properly. </p>



</body>

 <link>https://wiki.fsfe.org/Migrated/FellowshipElection_2017</link>

	<tags>
      <tag>front-page</tag>
      <tag content="Fellowship Election 2017">Fellowship Election</tag>
      <tag content="General Assembly">GA</tag>
      <tag content="Fellowship representative">Fellowship representative</tag>
	</tags>
	
  </news>
  
</newsset>







