<?xml version="1.0" encoding="utf-8"?>
<eventset>
  <version>1</version>
  <event start="2023-11-10" end="2023-11-10">
        <title>SFSCON '23 - Lettura di “Ada &amp; Zangemann” in italiano per le scuole (evento collaterale) a Bolzano</title>

    <body>
			<p>I bambini delle scuole sono invitati a partecipare alla lettura, in italiano, del libro “Ada &amp; Zangemann: A Tale of Software, Skateboards, and Raspberry Ice Cream”, che si terrà durante il primo giorno della SFSCON 2023.</p>
      <p>Questo libro illustrato per bambini racconta la storia del famoso inventore Zangemann e della bambina Ada, una curiosa armeggiatrice. Ada inizia a sperimentare con hardware e software e nel frattempo si rende conto di quanto sia cruciale per lei e per gli altri controllare la tecnologia.</p>
    </body>

    <link>https://www.sfscon.it/programs/2023/</link>
    <tags>
      <tag key="it">Italy</tag>      <tag key="talk"/>
      <tag key="front-page"/>
    </tags>
  </event>
</eventset>
