<?xml version="1.0" encoding="iso-8859-1" ?>

<newsset>
  <news date="2003-02-08">
    <title>Larry Lessig riceve il Premio della FSF per l'Avanzamento del Software Libero</title>
    <body>
        Comunicato stampa della Free Software Foundation: "Bruxelles,
	Belgio - Sabato 8 Febbraio 2003 - La Free Software Foundation
	(FSF) ha conferito oggi il suo quinto Premio per l'Avanzamento del 
        Software Libero. Il Presidente e fondatore della FSF, Richard 
        Stallman, ha consegnato il premio al Professor Lawrence Lessig per
        aver promosso la comprensione della dimensione politica del software 
        libero, compresa l'idea che "il codice è legge".  Lessig ha inoltre
        proposso idee simili al Software Libero in altri campi correlati."
    </body>
    <link>http://mail.fsfeurope.org/pipermail/press-release/2003q1/000050.html</link>
  </news>
</newsset>
