<?xml version="1.0" encoding="utf-8" ?>
<infoset>
  <info id="f-droid-poster">
    <!-- Leave a tag like <printready> blank or erase it if you don't 
    want to appear it -->
    <!-- Translations for "Type", "Size" etc. can be found in 
    /tools/texts-**.xml -->
    <name>Free Your Android - poter</name>
    <description>
      The poster to promote our <a href="http://www.freeyourandroid.org">"Free Your Android" campaign</a> for which there are flyers available, too. This poster proofed to be very eye-catching and attracts a lot of people at booths who ask about the backgrounds of this campaign. We recommend to use it at any booth or other public activity.
    </description>
    <type>Poster</type>
    <size>A1</size>
    <context><a href="http://www.freeyourandroid.org">Free Your Android campaign</a></context>
    
<!-- everything below this line uses native language names for each language or technical abbreviations respectively, so there is no need to transalate it from here on -->
    
    <languages>
	  <a href="http://fsfe.org/campaigns/android/artwork/DIN_A1_de.png">Deutsch</a>, 
      <a href="http://www.fsfe.org/campaigns/android/artwork/DIN_A1_en_xl.png">English</a>,
      <a href="http://fsfe.org/campaigns/android/artwork/DIN_A1_es.png">Español</a>,
      <a href="http://fsfe.org/campaigns/android/artwork/DIN_A1_el.png">Ελληνικάk</a>,  
      <a href="http://fsfe.org/campaigns/android/artwork/DIN_A1_fr.png">Français</a>
    
    </languages>
    <printed>
      English
    </printed>
    <license>CC-BY-SA 4.0</license>
    <author>Free Software Foundation Europe</author>
    <source>
	  <a href="http://fsfe.org/campaigns/android/artwork/DIN_A1_de.svg">Deutsch</a>, 
      <a href="http://www.fsfe.org/campaigns/android/artwork/DIN_A1_en.svg">English</a>,
      <a href="http://fsfe.org/campaigns/android/artwork/DIN_A1_es.svg">Español</a>,
      <a href="http://fsfe.org/campaigns/android/artwork/DIN_A1_el.svg">Ελληνικάk</a>,  
      <a href="http://fsfe.org/campaigns/android/artwork/DIN_A1_fr.svg">Français</a>
	</source> 
    <printready></printready>
  </info>

</infoset>
