<?xml version="1.0" encoding="utf-8" ?>

<newsset>
  <version>1</version>

  <news type="newsletter" date="2004-12-05">
    <title>FSF Europe newsletter</title>
    <body>
      <p>
      Themen:
      FSFE in Microsoft-Prozess weiterhin unbeirrbar,
      FSFE erlangt Beobachterstatus in der WIPO,
      Ausbau der weltweiten Kooperation,
      Zwei FSFE-Mitglieder auf der SFScon,
      Andere öffentliche Auftritte.
      </p>
    </body>
    <link>https://lists.fsfe.org/pipermail/press-release-de/2004q4/000057.html</link>
  </news>
</newsset>
