<?xml version="1.0" encoding="utf-8"?>

<eventset> 
	<event start="2015-07-25" end="2015-07-25"> 
 
		<title>Fellowship Meeting Franken in Bamberg, Germany</title> 
 
		<body> 
			<p>Am Samstag, 25. Juli ab 19:00 Uhr findet wieder das lokale FSFE-Treffen in Franken statt. Treffpunkt ist der Bamberger Hackerspace "Backspace", in unmittelbarer Nähe zum Bahnhof und zur Innenstadt.  Alle Freunde Freier Software sind herzlich willkommen vorbeizukommen

. </p> 
		</body> 
 
		<link>https://wiki.fsfe.org/FellowshipEvents/Fellowship%20Meeting%20Franken/Franconia</link> 
 

		<tags>
			<tag content="Bamberg">Bamberg</tag>
			<tag content="Deutschland">de</tag>
		</tags>

 
	</event> 
</eventset> 