<?xml version="1.0" encoding="UTF-8"?>

<eventset>
  <event start="2012-06-27" end="2012-06-27">
    <title>Richard Stallman gives a talk about "Free Software and education" in Marly-le-Roi, France</title>
    <body>
      <p>
On June 27, Richard Stallman gives a talk about "Free Software and education" in Marly-le-Roi. The event will take place at the Cinéma le Fontenelle - Place de la gare, Marly-le-Roi from 10.00 to 12.00. Please, register in order to participate in the event.
      </p>
    </body>
    <page>http://www.intertice.fr/interTICE-Logiciels-Libres</page>
    <tags>
	<tag>edu</tag>
      <tag>fr</tag>
      <tag>RMS</tag>
    </tags>
  </event>
</eventset>
