<?xml version="1.0" encoding="utf-8" ?>
 
<eventset>
  <version>1</version>

  <event start="2007-05-11" end="2007-05-13">
    <title>First Italian Conference on Free Software</title>
    <body>
      <p>
      FSFE will be present at the first Italian Conference on Free Software, 
      a conference intended to examine the state of the art in Free Software.
      The conference wants to be the point of meeting of all the subjects 
      that involved in the diffusion and in the use of the Free Software in Italy
      and all over the world, or undertaken, public corporate body,
      university, developers, researchers and impassioned, to know it and to
      start collaborations and projects.
      The conference will be a point of intersection for all of the subjects
      around Free Software both in Italy and world-wide.  It will provide a
      forum for public bodies, universities, developers and researchers to
      network, collaborate and initiate projects.<br/>

      This will be the first conference focusing on Free Software in science
      and is being organised by Hacklab Cosenza in collaboration of FSFE,
      University of Calabria.
      </p>
    </body>
    <link>http://hacklab.cosenzainrete.it/confsl07/index.php?lang=EN</link>

  </event>
</eventset>
