<?xml version="1.0" encoding="utf-8" ?>

<newsset>
  <news type="newsletter" date="2009-04-09">
    <title>FSFE Newsletter</title>
    <body>
      1. FSFE launches list of recommended Free Software lawyers
      2. FSFE action on IPRED2 "Criminalisation" Directive
      3. Transcript of Richard M. Stallman's speech in Brussels online
      4. FSFE at A2K2 conference in Yale Law School
      5. Georg Greve and Jonas Öberg in Belgrade, Serbia
      6. Ivan Jelic joining European Core Team of FSFE
      7. Merchandise available via web order
      8. Get active: join the translation team!
    </body>
    <link></link>
  </news>
</newsset>
