<?xml version="1.0" encoding="utf-8" ?>

<newsset>
  <news type="newsletter" date="2009-04-18">
    <title>FSFE Newsletter</title>
    <body>
      Falls du dich gewundert hast, wann der Newsletter wiederkommen würde,
      hör auf dich zu wundern – er ist zurück! Wir entschuldigen uns für das
      verspätete Versenden des Newsletters in den letzten Monaten und
      versichern dir, dass unser monatlicher Newsletter jetzt die Aufgabe
      übernimmt, dich regelmäßig über die Aktivitäten der FSFE auf dem
      Laufenden zu halten.
    </body>
    <link>http://mail.fsfeurope.org/pipermail/press-release-de/2009q2/000142.html</link>
  </news>
</newsset>
