<?xml version="1.0" encoding="utf-8" ?>

<newsset>
  <news type="newsletter" date="2009-04-09">
    <title>FSFE Newsletter</title>
    <body>
      1. La FSFE presenta una lista de abogados especialistas en Software Libre
      2. La FSFE protesta por la «criminalización» en la directiva IPRED2
      3. Publicamos la trascripción del discurso de Richard M. Stallman en Bruselas
      4. La FSFE en la conferencia A2K2 de la Facultad de Derecho de Yale
      5. Georg Greve y Jonas Öberg en Belgrado (Serbia)
      6. Ivan Jelic se une a al equipo de la FSFE
      7. Disponible la compra online de merchandising
      8. Manténgase activo: ¡Únase al equipo de traductores!
    </body>
    <link></link>
  </news>
</newsset>
