<?xml version="1.0" encoding="utf-8" ?>

<newsset>
  <news type="newsletter" date="2008-08-23">
    <title>FSFE Newsletter</title>
    <body>
      Über die letzten Monate hat die FSFE unterschiedliche Aktivitäten unternommen.
      Besonders vielversprechend ist die Zunahme regionaler Fellowship-Aktivitäten in
      ganz Europa. Wir freuen uns darauf, mehr lokale Gruppen entstehen zu sehen und
      vor allem von ihnen auf allen möglichen Ebenen zu hören. Mit das Wichtigste
      beim Unterstützen Freier Software ist, sein Wissen mit anderen zu teilen.
    </body>
    <link>http://mail.fsfeurope.org/pipermail/press-release-de/2008q3/000129.html</link>
  </news>
</newsset>
