<?xml version="1.0" encoding="UTF-8"?>
<newsset>
  <news date="2014-04-24">
    <title>Document Freedom Day 2014 Report Published</title>
    <body>

      <p>
Open Standards were celebrated to the ends of the earth for Document Freedom Day 2014, with 51 events in 22 countries. The campaign for interoperability was enacted from Tokyo to Rio, and Birmingham to Taipei.
     </p>

    </body>
    <link>http://documentfreedom.org/news/2014/news-20140424-01.en.html</link>
    <tags>
      <tag>front-page</tag>
      <tag>dfd</tag>
      <tag>en</tag>
      <tag>Open Standards</tag>
    </tags>
  </news>
</newsset>
