<?xml version="1.0" encoding="utf-8"?>
<eventset>
  <version>1</version>
  <event start="2024-02-03" end="2024-02-04">
        <title>FSFE with booth, talks and dev room at FOSDEM 2024</title>

    <body>
      <p>It is that time of the year again. FOSDEM will take place in Brussels on 3 and 4 February 2024. The Free Software Foundation Europe will be there with most of its staff and some of our volunteers!</p>
      <p>You can find a detailed overview of FSFE organized dev rooms and workshops <a href="/news/2024/news-20240130-01.html">in this news item</a>.</p>
      <p>We hope to see you at FOSDEM!</p>
    </body>

    <link>https://fosdem.org/2024/</link>
    <tags>
      <tag key="fosdem"/>
      <tag key="front-page"/>
      <tag key="talk"/>
      <tag key="workshop"/>
      <tag key="be"/>
    </tags>
  </event>
</eventset>
