<?xml version="1.0" encoding="utf-8"?>
<eventset>
  <version>1</version>
  <event start="2026-06-06T08:00:00Z" end="2026-06-07T13:00:00Z">
        <title>FSFE infobooth at T-DOSE conference in Geldrop, Netherlands</title>
    <group>
     <name>Netherlands</name> 
     <url></url>
    </group>

    <body>
      <p>The Netherlands team will be present at the Technical Dutch Open Source Event (T-DOSE) with an info booth. A good moment to exchange ideas and stock up on stickers and merchandise.</p>
     <p>The Technical Dutch Open Source Event (T-DOSE) is a free conference to promote the use and development of Open Source software. This event has is organised yearly since 2006 in the Brainport region, near Eindhoven, The Netherlands. During this event, Open Source projects, developers and visitors can exchange ideas and knowledge. </p>
    </body>

    <link>https://t-dose.org/2026/</link>
    <tags>
            <tag key="nl">
          Netherlands      </tag>
            <tag key="infobooth"/>
<tag key="localgroup"/>
      <tag key="front-page"/>
    </tags>
  </event>
</eventset>
