<?xml version="1.0" encoding="UTF-8"?>
<quotes>
    <quote>
      <photo>/fellowship/graphics/people/guidoguenther.jpg</photo>
      <text>
        Ik ben erg onder de indruk van wat de FSFE heeft bereikt op EN- en 
nationaal niveau. Toen ik nog werkte in de publieke sector heb ik een glimp kunnen opvangen van de 
enorme hoeveelheden geld die worden uitgegeven aan het lobbyen voor niet-vrije software en de 
zogenoemde industrie-standaarden in Duitsland en de EU. Het is verbazingwekkend om te zien hoe de 
FSFE het nog steeds voor elkaar krijgt om te worden gehoord. Dit steunen was een van mijn motivaties 
om een Fellow te worden.
      </text>
      <author>Guido Günther (Freelancer en Debian-ontwikkelaar)</author>
    </quote>
</quotes>
