<?xml version="1.0" encoding="UTF-8"?>
<quotes>
    <quote>
        <author>Greg Kroah-Hartman (Linux Kernel Developer)</author>
        <photo>/fellowship/graphics/people/kroahhartman.jpg</photo>
	<text>
	  The "Public Money - Public Code" campaign, as well as the "REUSE
	  Initiative" made me notice that the FSFE is an organization which
	  supports the same ideals that I do. I want to help them do more great
	  things, and so now I am proud FSFE supporter.
        </text>
    </quote>
</quotes>
