<?xml version="1.0" encoding="UTF-8"?>

<textset>
  <!-- Footer -->
  <text id="lastchanged"> Última actualización: </text>
  <text id="translator1a">Agradecemos a </text>
  <text id="translator1b"> la traducción de esta página. </text>
  <text id="translator2">Ésta es una traducción no oficial. </text>
  <text id="translator3a">También puede consultar el </text>
  <text id="translator3b">texto original</text>
  <text id="translator3c">.</text>
  <text id="permission">
      Se permite la copia y distribución de este documento completo
      en cualquier medio, siempre que se incluya este aviso.
  </text>
  <text id="webmaster">
    Por favor, informe de los problemas de esta página a
    <em>webmaster en fsfeurope.org</em>.
  </text>
  <text id="fsfnetwork">
    La FSFE tiene <a href="/about/fsfnetwork.html">organizaciones hermanas</a> en <a
      href="//www.fsf.org/">América del Norte</a>, <a
      href="http://fsf.org.in/">India</a> y <a
      href="http://www.fsfla.org/">América Latina</a>.
  </text>
  <text id="outdated">
    <strong>Aviso: </strong>
    Esta página puede estar desactualizada con respecto a la original.
    Por favor, consulte
    <a href="/contribute/contribute.html">esta página</a> para informarse de 
    cómo puede ayudar con las traducciones y hacer otras contribuciones.
  </text>
  <text id="notranslation">
    <strong>Aviso: </strong>
    Esta página no se ha traducido todavía. Lo que está viendo es
    la versión original de la página. Por favor, consulte
    <a href="/contribute/contribute.html">esta página</a> para informarse de 
    cómo puede ayudar con las traducciones y hacer otras contribuciones.
  </text>

  <text id="source">Código fuente</text>
  <text id="contact-us">Contáctenos</text>
  <text id="translate">Traducir esta página?</text>
<!-- Info Box -->
  <text id="search">Buscar</text>
  <text id="submit">Buscar</text>

  <text id="language">Idioma</text>

 <!-- Article metadata -->
 <text id="author">Autor</text>
 <text id="published">Publicado</text>

 <text id="download">Bajar</text>
  <!-- Conjunctions -->
  <text id="to">a</text>

<!-- Menu -->
  <text id="fsfe/about">Acerca de</text>
  <text id="fsfe/projects">Proyectos</text>
  <text id="fsfe/documents">Documentos</text>
  <text id="fsfe/help">Colabore</text>
  <text id="fsfe/donate">Donaciones</text>
  <text id="fsfe/order">Tienda</text>
  <text id="fsfe/lists">Listas de correo</text>
  <text id="fsfe/press">Prensa</text>
  <text id="fsfe/thankgnus">Gracias GNUs</text>
  <text id="support/support">Support</text>
  <text id="fellowship/fellowship">Join</text>
  <text id="fellowship/1-wiki">Wiki</text>
  <text id="fellowship/2-planet">Planet Blog</text>
  <text id="fellowship/3-join">Únase</text>
  
  <!-- Date time -->
  <text id="months/1">Enero</text>
  <text id="months/2">Febrero</text>
  <text id="months/3">Marzo</text>
  <text id="months/4">Abril</text>
  <text id="months/5">Mayo</text>
  <text id="months/6">Junio</text>
  <text id="months/7">Julio</text>
  <text id="months/8">Agosto</text>
  <text id="months/9">Septiembre</text>
  <text id="months/10">Octubre</text>
  <text id="months/11">Noviembre</text>
  <text id="months/12">Diciembre</text>
 
  <text id="months-abbreviated/1">Ene</text>
  <text id="months-abbreviated/2">Feb</text>
  <text id="months-abbreviated/3">Mar</text>
  <text id="months-abbreviated/4">Abr</text>
  <text id="months-abbreviated/5">May</text>
  <text id="months-abbreviated/6">Jun</text>
  <text id="months-abbreviated/7">Jul</text>
  <text id="months-abbreviated/8">Ago</text>
  <text id="months-abbreviated/9">Sep</text>
  <text id="months-abbreviated/10">Oct</text>
  <text id="months-abbreviated/11">Nov</text>
  <text id="months-abbreviated/12">Dic</text>

  <text id="weekdays/1">Lunes</text>
  <text id="weekdays/2">Martes</text>
  <text id="weekdays/3">Miércoles</text>
  <text id="weekdays/4">Jueves</text>
  <text id="weekdays/5">Viernes</text>
  <text id="weekdays/6">Sábado</text>
  <text id="weekdays/7">Domingo</text>

  <text id="weekdays-abbreviated/1">Lun</text>
  <text id="weekdays-abbreviated/2">Mar</text>
  <text id="weekdays-abbreviated/3">Mie</text>
  <text id="weekdays-abbreviated/4">Jue</text>
  <text id="weekdays-abbreviated/5">Vie</text>
  <text id="weekdays-abbreviated/6">Sab</text>
  <text id="weekdays-abbreviated/7">Dom</text>
  
  <text id="statement1">La Free Software Foundation Europe es una organización sin ánimo de lucro dedicada a la promoción del </text>
  <text id="statement-fs">Software Libre</text>
  <text id="statement2"> que trabaja en favor de la libertad en la sociedad de la información</text>
  
  <text id="learn-more">Saber más</text>
  
  <text id="news">Últimas noticias</text>
  <text id="receive-newsletter">Recibir la newsletter mensual de la FSFE</text>

  <text id="events">Próximos eventos</text>
  <text id="more">Leer más</text>
  <text id="morenews">Más noticias…</text>
  <text id="moreevents">Más eventos…</text>
  
  <!-- Campaign box on front-page, translated texts -->
  <text id="cb-restricted-boot">El 14 de Febrero: </text>
  <text id="cb-restricted-boot-link">Muestra tu amor por el Software Libre</text>
  <!-- end of texts for the campaign box -->
  
  <text id="donate">Donaciones</text>
  <text id="join">Únase</text>  

  <text id="subscribe">Registrarse</text>
  
  <!-- petitions -->
  <text id="osig">Organizaciones</text>
  <text id="isig">Individuos</text>
  
</textset>
