<?xml version="1.0" encoding="utf-8" ?>
 
<eventset>
  <version>1</version>

  <event start="2007-03-24" end="2007-03-24">
    <title>Premières rencontres de la Fellowship en Franconie (Allemagne)</title>
    <body>
    Les premières rencontres de la Fellowship en Franconie auront lieu le 24 mars 2007 à Forchheim. Le rendez-vous est fixé à 16h00 au restaurant "Roter Ochs". Jutta Horstmann nous parlera des gestionnaires de contenu (CMS), Rainer Kersten du bureau de la FSFE nous donnera quelques informations sur la fondation, et la discussion qui s'en suivra sera certainement très intéressante :-).
    </body>
  </event>  
</eventset> 
