<?xml version="1.0" encoding="utf-8"?>

<eventset>
  <version>0</version>

  <event start="2010-06-30" end="2010-06-30">
    <title>Συνάντηση της Κοινότητας στο Άαχεν</title>

    <body>
      <p>
      Την Τετάρτη, 30 Ιουνίου 2010, η πρώτη συνάντηση της Κοινότητας του Άαχεν 
      θα πραγματοποιηθεί στο "Labyrinth", Pontstr. 156, 52062 Aachen.
      Ο πρόεδρος του FSFE Karsten Gerloff θα παρευρεθεί επίσης. Εκείνο το απόγευμα, 
      δεν υπάρχει ποδοσφαιρικός αγώνας του παγκοσμίου κυπέλλου στο πρόγραμμα.
      Οι επισκέπτες είναι ευπρόσδεκτοι!
     </p>
   </body>
  </event>
</eventset>
