<?xml version="1.0" encoding="UTF-8"?>
<eventset>
  <version>1</version>

  
  <event start="2010-05-06" end="2010-05-06">
    <title>Fellowship-meeting in Gothenburg</title>
    <body>
      On 6 May it is once again time for a Fellowship-meeting in
      Gothenburg.  The meeting will be held at <a
        href="http://gnutiken.se/">Gnutiken</a> in Övre Husargatan 27,
      and will commence at 6 pm.  Everyone are invited.
    </body>
  <tags>
    <tag key="se"/>
  </tags>
  </event>
</eventset>

