<?xml version="1.0" encoding="UTF-8" ?>

<eventset>
  <version>1</version>

  <event start="2004-06-23" end="2004-06-26">
    <title>GNU/LinuxTag in Karlsruhe, Duitsland</title>
    <body>
      GNU/LinuxTag is één van de belangrijkste Vrije Software
      evenementen. Ook dit jaar zal de FSF Europe weer een stand
      hebben. Meerdere leden van ons team zullen er zijn om vragen
      over onze activiteiten te beantwoorden, en we zullen merchandise
      zoals t-shirts en pins verkopen ten gunste van ons werk voor
      Vrije Software.
    </body>
    <page>http://www.linuxtag.org/2004/index.html</page>
  </event>
</eventset>

