<?xml version="1.0" encoding="utf-8"?>
 
<eventset>
  <version>1</version>

  <event start="2009-11-16" end="2009-11-20">
    <title>Συνάντηση του WIPO για την υλοποίηση της Ημερήσιας Διάταξης για την Ανάπτυξη,
    Γενεύη, Ελβετία</title>
    <body>
      <p>
        Χάρη στη συνεπή υποστήριξη του FSFE και άλλων οργανισμών,
        η Ημερήσια Διάταξη για την Ανάπτυξη του WIPO είναι επί τέλους
        καθ' οδόν προς την εφαρμογή της. Ο Πρόεδρος του FSFE Karsten
        Gerloff θα συμμετάσχει στη συνάντηση της Επιτροπής από τις
        16 ως τις 20 Νοεμβρίου για να διασφαλίσει ότι το Ελεύθερο
        Λογισμικό και τα Ανοιχτά Πρότυπα θα έχουν τη θέση τους στη διαδικασία.

        Το FSFE είναι επίσημος παρατηρητής στο WIPO. Η εκδήλωση δεν είναι ανοιχτή στο κοινό.
      </p>
    </body>
  </event>
</eventset>
