<?xml version="1.0" encoding="utf-8"?>
 
<eventset>
  <version>1</version>

  <event start="2009-03-03" end="2009-03-03">
    <title>Keynote by FSFE president Georg Greve at CeBIT, Hanover, Germany</title>
    <body>
      Georg Greve, president of the FSFE will deliver a keynote speech entitled 
      "To dare more freedom" at the CeBIT in Hanover (Hall 6, Open Source
      Forum). The keynote is scheduled on 3 March 2009 at 11:00hrs and will be
      delivered in English. 
      <br/>      
    </body>
    <page>http://www.cebit.de/</page>
  </event>
</eventset>
