<?xml version="1.0" encoding="utf-8"?>
 
<eventset>
  <version>1</version>

  <event start="2009-07-17" end="2009-07-17">
	  <title>Monatliches Fellowship-Treffen in Wien</title>
    <body>
	Diesen Monat findet das Treffen der Wiener Fellowship-Gruppe wieder im 
	<a href="http://metalab.at/wiki/Lage" title="Metalab location">Metalab</a>
	in der Rathausstraße 6 im ersten Wiener Gemeindebezirk statt. Wir treffen uns 
	ab 18:00 Uhr, die Agenda starten wir um 19:00 Uhr. Diesmal wird Matthias Kirschner, 
	Fellowship-Koordinator der FSFE, an unserem Treffen teilnehmen und Fragen zum Fellowship 
	und der FSFE beantworten. Wie immer richtet sich diese Einladung an alle, die sich für 
	Freie Software oder die FSFE interessieren. Wir freuen uns auf zahlreiche Besucher!
    </body>
  </event>
</eventset>
