<?xml version="1.0" encoding="utf-8"?>
<eventset>
  <version>1</version>
  <event start="2022-02-16" end="2022-02-16">
        <title>Lecture Free Software and Open Data (online)</title>

    <body>
      <p>Dr. Lucas Lasota, FSFE Legal Project Manager and Researcher at Humboldt University of Berlin, invites Robbie Morrison to give a lecture at the Seminar 'Introduction to Software Law' about the intersection of Free Software and Open Data. Robbie Morrison is a researcher, engineer and software developer. He is specialist in the field of open data and energy systems.</p>
      <p>The lecture will be held online and it is free from registration. The language of the event will be English.</p>
      <p>Here is the summary:</p>
      <p>What: Lecture &quot;Open Source Software and Open Data&quot;<br />
When: 16.02.2022 at 14:15 CET<br />
Where: https://bbb.hu-berlin.de/b/luc-b9t-2c7-kr4</p>
    </body>

    <link>https://box.hu-berlin.de/f/829f85ab944f47fda0bd/</link>
    <tags>
            <tag key="talk"/>
      <tag key="front-page"/>
    </tags>
  </event>
</eventset>